{
    "homepage": "https://www.kiwix.org/",
    "description": "The Kiwix Desktop is a viewer/manager of ZIM files for GNU/Linux and Microsoft Windows OSes.",
    "license": {
        "identifier": "GPL-3.0",
        "url": "https://github.com/kiwix/kiwix-desktop/blob/master/LICENSE"
    },
    "version": "2.3.0",
    "url": "https://download.kiwix.org/release/kiwix-desktop/kiwix-desktop_windows_x64_2.3.0.zip",
    "hash": "3349855ef00447b830b814ad5670f75b6b29c352292d3cd6a69d13961bd0096a",
    "installer": {
        "script": "Move-Item \"$dir\\kiwix-desktop_windows_x64_$version\\*\" \"$dir\\\""
    },
    "shortcuts": [
        [
            "kiwix-desktop.exe",
            "Kiwix"
        ]
    ],
    "checkver": {
        "url": "https://download.kiwix.org/release/kiwix-desktop/?C=M;O=D",
        "regex": "kiwix-desktop_windows_x64_([\\d.-]+?).zip"
    },
    "autoupdate": {
        "url": "https://download.kiwix.org/release/kiwix-desktop/kiwix-desktop_windows_x64_$version.zip"
    }
}
